tabular-print/__init__.py
tabular-print/tabular_print.py
tabular_print/__init__.py
tabular_print/tabular_print.py
tabular_print-1.0.7a1.dist-info/DESCRIPTION.rst
tabular_print-1.0.7a1.dist-info/METADATA
tabular_print-1.0.7a1.dist-info/RECORD
tabular_print-1.0.7a1.dist-info/WHEEL
tabular_print-1.0.7a1.dist-info/metadata.json
tabular_print-1.0.7a1.dist-info/top_level.txt
tabularprint/__init__.py
tabularprint/tabularprint.py
