Metadata-Version: 2.0
Name: tabular-print
Version: 1.0.7a1
Summary: Lightweight, tabular data, printing module for Python.
Home-page: https://github.com/mkitzan/tabular-print
Author: Michael Kitzan
Author-email: mkitzan45@gmail.com
License: MIT
Keywords: tabular-data sqlite3 python data table
Platform: UNKNOWN
Classifier: Intended Audience :: Developers
Classifier: Intended Audience :: Information Technology
Classifier: Intended Audience :: Science/Research
Classifier: Intended Audience :: System Administrators
Classifier: Intended Audience :: Other Audience
Classifier: License :: OSI Approved :: MIT License
Classifier: Programming Language :: Python :: 3
Classifier: Programming Language :: Python :: 3.6
Classifier: Programming Language :: Python :: 3 :: Only
Classifier: Development Status :: 3 - Alpha
Classifier: Topic :: Database
Classifier: Topic :: Scientific/Engineering :: Visualization
